<annotation verified="yes">
	<folder>Frame 1-25 x 0.5seg</folder>
	<filename>501910.jpg</filename>
	<path>C:\Users\braya\Frame 1-25 x 0.5seg\501910.jpg</path>
	<source>
		<database>Unknown</database>
	</source>
	<size>
		<width>800</width>
		<height>600</height>
		<depth>3</depth>
	</size>
	<segmented>0</segmented>
	<object>
		<name>Revolver</name>
		<pose>Unspecified</pose>
		<truncated>0</truncated>
		<difficult>0</difficult>
		<bndbox>
			<xmin>150</xmin>
			<ymin>246</ymin>
			<xmax>327</xmax>
			<ymax>435</ymax>
		</bndbox>
	</object>
	<object>
		<name>Pistola</name>
		<pose>Unspecified</pose>
		<truncated>0</truncated>
		<difficult>0</difficult>
		<bndbox>
			<xmin>444</xmin>
			<ymin>147</ymin>
			<xmax>649</xmax>
			<ymax>408</ymax>
		</bndbox>
	</object>
</annotation>
